sqlitepy/__init__.py
sqlitepy/sqlitepy.py
sqlitepy-0.1.2.dist-info/LICENSE
sqlitepy-0.1.2.dist-info/METADATA
sqlitepy-0.1.2.dist-info/WHEEL
sqlitepy-0.1.2.dist-info/top_level.txt
sqlitepy-0.1.2.dist-info/RECORD
