Metadata-Version: 2.1
Name: sqlitepy
Version: 0.1.2
Summary: Human interface for sqlite3
Home-page: UNKNOWN
Author: Ginajarn
License: UNKNOWN
Platform: UNKNOWN
Classifier: Programming Language :: Python :: 3
Classifier: License :: OSI Approved :: MIT License
Classifier: Operating System :: OS Independent
Requires-Python: >=3
